{
  "meta": {
    "total": 198,
    "version": "1.0",
    "description": "KET高频词汇+标准例句库 四年级4个月冲刺版"
  },
  "words": [
    {
      "id": 1,
      "word": "able",
      "phonetic": "/ˈeɪbl/",
      "part": "adj.",
      "meaning": "有能力的，能够",
      "topic": "人物性格&能力",
      "topic_en": "character",
      "level": "A",
      "sentence1": "I am **able** to swim very well.",
      "sentence1_cn": "我很会游泳。",
      "sentence2": "She is **able** to finish her homework on time.",
      "sentence2_cn": "她能按时完成作业。"
    },
    {
      "id": 2,
      "word": "active",
      "phonetic": "/ˈæktɪv/",
      "part": "adj.",
      "meaning": "积极的，活跃的",
      "topic": "人物性格&能力",
      "topic_en": "character",
      "level": "A",
      "sentence1": "My little brother is very **active** at school.",
      "sentence1_cn": "我弟弟在学校很活跃。",
      "sentence2": "She likes **active** sports like running and swimming.",
      "sentence2_cn": "她喜欢跑步和游泳这样的运动。"
    },
    {
      "id": 3,
      "word": "brave",
      "phonetic": "/breɪv/",
      "part": "adj.",
      "meaning": "勇敢的",
      "topic": "人物性格&能力",
      "topic_en": "character",
      "level": "A",
      "sentence1": "The boy was very **brave** at the dentist.",
      "sentence1_cn": "那个男孩在牙医那里非常勇敢。",
      "sentence2": "You must be **brave** when you feel scared.",
      "sentence2_cn": "当你感到害怕时，要勇敢。"
    },
    {
      "id": 4,
      "word": "calm",
      "phonetic": "/kɑːm/",
      "part": "adj.",
      "meaning": "冷静的",
      "topic": "人物性格&能力",
      "topic_en": "character",
      "level": "A",
      "sentence1": "Please stay **calm** and listen to the teacher.",
      "sentence1_cn": "请保持冷静，听老师说话。",
      "sentence2": "She is always **calm** before her exams.",
      "sentence2_cn": "她考试前总是很冷静。"
    },
    {
      "id": 5,
      "word": "careful",
      "phonetic": "/ˈkeəfl/",
      "part": "adj.",
      "meaning": "小心的，仔细的",
      "topic": "人物性格&能力",
      "topic_en": "character",
      "level": "A",
      "sentence1": "Be **careful** when you cross the road.",
      "sentence1_cn": "过马路时要小心。",
      "sentence2": "She is very **careful** with her schoolwork.",
      "sentence2_cn": "她对学业非常仔细认真。"
    },
    {
      "id": 6,
      "word": "clever",
      "phonetic": "/ˈklevə/",
      "part": "adj.",
      "meaning": "聪明的",
      "topic": "人物性格&能力",
      "topic_en": "character",
      "level": "A",
      "sentence1": "My friend is very **clever** at maths.",
      "sentence1_cn": "我的朋友数学很聪明。",
      "sentence2": "That was a **clever** answer to the question.",
      "sentence2_cn": "那是对这道题非常聪明的回答。"
    },
    {
      "id": 7,
      "word": "confident",
      "phonetic": "/ˈkɒnfɪdənt/",
      "part": "adj.",
      "meaning": "自信的",
      "topic": "人物性格&能力",
      "topic_en": "character",
      "level": "A",
      "sentence1": "She felt very **confident** before the show.",
      "sentence1_cn": "演出前她感到非常自信。",
      "sentence2": "He is **confident** about his English test.",
      "sentence2_cn": "他对英语考试很有信心。"
    },
    {
      "id": 8,
      "word": "creative",
      "phonetic": "/kriˈeɪtɪv/",
      "part": "adj.",
      "meaning": "有创造力的",
      "topic": "人物性格&能力",
      "topic_en": "character",
      "level": "A",
      "sentence1": "My sister is very **creative** and loves painting.",
      "sentence1_cn": "我姐姐很有创造力，喜欢画画。",
      "sentence2": "We need **creative** ideas for the school project.",
      "sentence2_cn": "我们需要有创意的想法来做学校项目。"
    },
    {
      "id": 9,
      "word": "friendly",
      "phonetic": "/ˈfrendli/",
      "part": "adj.",
      "meaning": "友好的",
      "topic": "人物性格&能力",
      "topic_en": "character",
      "level": "A",
      "sentence1": "The new teacher is very **friendly** to all students.",
      "sentence1_cn": "新老师对所有学生都很友好。",
      "sentence2": "Everyone in my class is **friendly** and helpful.",
      "sentence2_cn": "我班上的每个人都友好且乐于助人。"
    },
    {
      "id": 10,
      "word": "generous",
      "phonetic": "/ˈdʒenərəs/",
      "part": "adj.",
      "meaning": "大方的，慷慨的",
      "topic": "人物性格&能力",
      "topic_en": "character",
      "level": "A",
      "sentence1": "My grandfather is very **generous** with his money.",
      "sentence1_cn": "我爷爷花钱很大方。",
      "sentence2": "She is **generous** and always shares her food.",
      "sentence2_cn": "她很慷慨，总是分享她的食物。"
    },
    {
      "id": 11,
      "word": "honest",
      "phonetic": "/ˈɒnɪst/",
      "part": "adj.",
      "meaning": "诚实的",
      "topic": "人物性格&能力",
      "topic_en": "character",
      "level": "A",
      "sentence1": "It is important to be **honest** with your friends.",
      "sentence1_cn": "对朋友诚实是很重要的。",
      "sentence2": "An **honest** person always tells the truth.",
      "sentence2_cn": "诚实的人总是说实话。"
    },
    {
      "id": 12,
      "word": "kind",
      "phonetic": "/kaɪnd/",
      "part": "adj.",
      "meaning": "善良的",
      "topic": "人物性格&能力",
      "topic_en": "character",
      "level": "A",
      "sentence1": "It was very **kind** of you to help me.",
      "sentence1_cn": "你帮助我真是太好了。",
      "sentence2": "She is **kind** to animals and loves cats.",
      "sentence2_cn": "她对动物很善良，喜欢猫。"
    },
    {
      "id": 13,
      "word": "lazy",
      "phonetic": "/ˈleɪzi/",
      "part": "adj.",
      "meaning": "懒惰的",
      "topic": "人物性格&能力",
      "topic_en": "character",
      "level": "A",
      "sentence1": "Don't be **lazy** – finish your homework first.",
      "sentence1_cn": "不要懒惰，先把作业做完。",
      "sentence2": "My cat is very **lazy** and sleeps all day.",
      "sentence2_cn": "我的猫很懒，整天睡觉。"
    },
    {
      "id": 14,
      "word": "patient",
      "phonetic": "/ˈpeɪʃnt/",
      "part": "adj.",
      "meaning": "有耐心的",
      "topic": "人物性格&能力",
      "topic_en": "character",
      "level": "A",
      "sentence1": "Good teachers are always **patient** with their students.",
      "sentence1_cn": "好老师总是对学生很有耐心。",
      "sentence2": "You need to be **patient** when you learn a new skill.",
      "sentence2_cn": "学习新技能时需要有耐心。"
    },
    {
      "id": 15,
      "word": "polite",
      "phonetic": "/pəˈlaɪt/",
      "part": "adj.",
      "meaning": "有礼貌的",
      "topic": "人物性格&能力",
      "topic_en": "character",
      "level": "A",
      "sentence1": "It is **polite** to say thank you after a meal.",
      "sentence1_cn": "饭后说谢谢是有礼貌的。",
      "sentence2": "She is always **polite** and says please and thank you.",
      "sentence2_cn": "她总是很有礼貌，说请和谢谢。"
    },
    {
      "id": 16,
      "word": "quiet",
      "phonetic": "/ˈkwaɪət/",
      "part": "adj.",
      "meaning": "安静的",
      "topic": "人物性格&能力",
      "topic_en": "character",
      "level": "A",
      "sentence1": "Please be **quiet** in the library.",
      "sentence1_cn": "在图书馆请保持安静。",
      "sentence2": "She is a **quiet** girl but very clever.",
      "sentence2_cn": "她是个安静的女孩，但很聪明。"
    },
    {
      "id": 17,
      "word": "shy",
      "phonetic": "/ʃaɪ/",
      "part": "adj.",
      "meaning": "害羞的",
      "topic": "人物性格&能力",
      "topic_en": "character",
      "level": "A",
      "sentence1": "He is too **shy** to speak in front of the class.",
      "sentence1_cn": "他太害羞了，不敢在全班面前讲话。",
      "sentence2": "She was **shy** on her first day at school.",
      "sentence2_cn": "她第一天上学时很害羞。"
    },
    {
      "id": 18,
      "word": "smart",
      "phonetic": "/smɑːt/",
      "part": "adj.",
      "meaning": "机灵的，聪明的",
      "topic": "人物性格&能力",
      "topic_en": "character",
      "level": "A",
      "sentence1": "That was a very **smart** idea!",
      "sentence1_cn": "那是个非常聪明的主意！",
      "sentence2": "She is **smart** and always gets good marks.",
      "sentence2_cn": "她很聪明，总是得高分。"
    },
    {
      "id": 19,
      "word": "strict",
      "phonetic": "/strɪkt/",
      "part": "adj.",
      "meaning": "严格的",
      "topic": "人物性格&能力",
      "topic_en": "character",
      "level": "A",
      "sentence1": "Our maths teacher is very **strict** about homework.",
      "sentence1_cn": "我们的数学老师对作业非常严格。",
      "sentence2": "My parents are **strict** but they care about me.",
      "sentence2_cn": "我的父母很严格，但他们关心我。"
    },
    {
      "id": 20,
      "word": "thoughtful",
      "phonetic": "/ˈθɔːtfl/",
      "part": "adj.",
      "meaning": "体贴的",
      "topic": "人物性格&能力",
      "topic_en": "character",
      "level": "A",
      "sentence1": "It was **thoughtful** of her to bring me a gift.",
      "sentence1_cn": "她给我带礼物真是很体贴。",
      "sentence2": "He is a **thoughtful** son and always helps his mother.",
      "sentence2_cn": "他是个体贴的儿子，总是帮助妈妈。"
    },
    {
      "id": 21,
      "word": "attend",
      "phonetic": "/əˈtend/",
      "part": "v.",
      "meaning": "参加，出席",
      "topic": "校园学习&日常动作",
      "topic_en": "school",
      "level": "A",
      "sentence1": "All students must **attend** the morning meeting.",
      "sentence1_cn": "所有学生必须参加早上的会议。",
      "sentence2": "Did you **attend** the school sports day last week?",
      "sentence2_cn": "你上周参加学校运动日了吗？"
    },
    {
      "id": 22,
      "word": "borrow",
      "phonetic": "/ˈbɒrəʊ/",
      "part": "v.",
      "meaning": "借入，借",
      "topic": "校园学习&日常动作",
      "topic_en": "school",
      "level": "A",
      "sentence1": "Can I **borrow** your pen, please?",
      "sentence1_cn": "请问我能借你的笔吗？",
      "sentence2": "She **borrowed** a book from the school library.",
      "sentence2_cn": "她从学校图书馆借了一本书。"
    },
    {
      "id": 23,
      "word": "complete",
      "phonetic": "/kəmˈpliːt/",
      "part": "v.",
      "meaning": "完成",
      "topic": "校园学习&日常动作",
      "topic_en": "school",
      "level": "A",
      "sentence1": "Please **complete** your homework before dinner.",
      "sentence1_cn": "请在晚饭前完成你的作业。",
      "sentence2": "He **completed** all the questions in the test.",
      "sentence2_cn": "他完成了考试中的所有题目。"
    },
    {
      "id": 24,
      "word": "copy",
      "phonetic": "/ˈkɒpi/",
      "part": "v.",
      "meaning": "抄写，复制",
      "topic": "校园学习&日常动作",
      "topic_en": "school",
      "level": "A",
      "sentence1": "Please **copy** the sentences into your notebook.",
      "sentence1_cn": "请把句子抄写到你的笔记本上。",
      "sentence2": "Do not **copy** your friend's answers in the test.",
      "sentence2_cn": "考试中不要抄你朋友的答案。"
    },
    {
      "id": 25,
      "word": "discuss",
      "phonetic": "/dɪˈskʌs/",
      "part": "v.",
      "meaning": "讨论",
      "topic": "校园学习&日常动作",
      "topic_en": "school",
      "level": "A",
      "sentence1": "Let's **discuss** our plans for the school trip.",
      "sentence1_cn": "我们来讨论一下学校旅行的计划。",
      "sentence2": "The class **discussed** the story for ten minutes.",
      "sentence2_cn": "全班讨论了这个故事十分钟。"
    },
    {
      "id": 26,
      "word": "explain",
      "phonetic": "/ɪkˈspleɪn/",
      "part": "v.",
      "meaning": "解释",
      "topic": "校园学习&日常动作",
      "topic_en": "school",
      "level": "A",
      "sentence1": "Can you **explain** the rule again, please?",
      "sentence1_cn": "请你再解释一遍这个规则好吗？",
      "sentence2": "The teacher **explained** the new words clearly.",
      "sentence2_cn": "老师清楚地解释了新单词。"
    },
    {
      "id": 27,
      "word": "finish",
      "phonetic": "/ˈfɪnɪʃ/",
      "part": "v.",
      "meaning": "结束，完成",
      "topic": "校园学习&日常动作",
      "topic_en": "school",
      "level": "A",
      "sentence1": "I **finished** my homework before dinner.",
      "sentence1_cn": "我在晚饭前完成了作业。",
      "sentence2": "Have you **finished** reading that book yet?",
      "sentence2_cn": "你读完那本书了吗？"
    },
    {
      "id": 28,
      "word": "forget",
      "phonetic": "/fəˈɡet/",
      "part": "v.",
      "meaning": "忘记",
      "topic": "校园学习&日常动作",
      "topic_en": "school",
      "level": "A",
      "sentence1": "Don't **forget** to bring your school bag tomorrow.",
      "sentence1_cn": "别忘了明天带你的书包。",
      "sentence2": "She **forgot** her lunch at home this morning.",
      "sentence2_cn": "今天早上她把午饭忘在家里了。"
    },
    {
      "id": 29,
      "word": "join",
      "phonetic": "/dʒɔɪn/",
      "part": "v.",
      "meaning": "加入",
      "topic": "校园学习&日常动作",
      "topic_en": "school",
      "level": "A",
      "sentence1": "Would you like to **join** our reading club?",
      "sentence1_cn": "你想加入我们的阅读俱乐部吗？",
      "sentence2": "He **joined** the school football team last year.",
      "sentence2_cn": "他去年加入了学校足球队。"
    },
    {
      "id": 30,
      "word": "learn",
      "phonetic": "/lɜːn/",
      "part": "v.",
      "meaning": "学习",
      "topic": "校园学习&日常动作",
      "topic_en": "school",
      "level": "A",
      "sentence1": "I am learning to **learn** new English words every day.",
      "sentence1_cn": "我每天都在学新的英语单词。",
      "sentence2": "She **learnt** to ride a bike when she was six.",
      "sentence2_cn": "她六岁时学会了骑自行车。"
    },
    {
      "id": 31,
      "word": "lend",
      "phonetic": "/lend/",
      "part": "v.",
      "meaning": "借出",
      "topic": "校园学习&日常动作",
      "topic_en": "school",
      "level": "A",
      "sentence1": "Can you **lend** me your ruler for a minute?",
      "sentence1_cn": "你能把你的尺借给我一下吗？",
      "sentence2": "She **lent** her dictionary to her classmate.",
      "sentence2_cn": "她把词典借给了她的同学。"
    },
    {
      "id": 32,
      "word": "miss",
      "phonetic": "/mɪs/",
      "part": "v.",
      "meaning": "错过，想念",
      "topic": "校园学习&日常动作",
      "topic_en": "school",
      "level": "A",
      "sentence1": "I **missed** the school bus this morning.",
      "sentence1_cn": "今天早上我错过了校车。",
      "sentence2": "She **misses** her old friends from primary school.",
      "sentence2_cn": "她很想念小学时的老朋友。"
    },
    {
      "id": 33,
      "word": "practise",
      "phonetic": "/ˈpræktɪs/",
      "part": "v.",
      "meaning": "练习",
      "topic": "校园学习&日常动作",
      "topic_en": "school",
      "level": "A",
      "sentence1": "You should **practise** your English every day.",
      "sentence1_cn": "你应该每天练习英语。",
      "sentence2": "She **practised** the piano for one hour after school.",
      "sentence2_cn": "她放学后练了一个小时的钢琴。"
    },
    {
      "id": 34,
      "word": "prepare",
      "phonetic": "/prɪˈpeə/",
      "part": "v.",
      "meaning": "准备",
      "topic": "校园学习&日常动作",
      "topic_en": "school",
      "level": "A",
      "sentence1": "I **prepared** my bag the night before school.",
      "sentence1_cn": "我在上学前一晚准备好了书包。",
      "sentence2": "Let's **prepare** for the English test together.",
      "sentence2_cn": "让我们一起为英语考试做准备。"
    },
    {
      "id": 35,
      "word": "promise",
      "phonetic": "/ˈprɒmɪs/",
      "part": "v.",
      "meaning": "承诺",
      "topic": "校园学习&日常动作",
      "topic_en": "school",
      "level": "A",
      "sentence1": "I **promise** to finish my homework tonight.",
      "sentence1_cn": "我答应今晚完成作业。",
      "sentence2": "She **promised** her mum to be home by five.",
      "sentence2_cn": "她答应妈妈五点前回家。"
    },
    {
      "id": 36,
      "word": "remember",
      "phonetic": "/rɪˈmembə/",
      "part": "v.",
      "meaning": "记得",
      "topic": "校园学习&日常动作",
      "topic_en": "school",
      "level": "A",
      "sentence1": "**Remember** to take your book to class.",
      "sentence1_cn": "记得带你的书去上课。",
      "sentence2": "Do you **remember** the words from last week?",
      "sentence2_cn": "你记得上周的单词吗？"
    },
    {
      "id": 37,
      "word": "repeat",
      "phonetic": "/rɪˈpiːt/",
      "part": "v.",
      "meaning": "重复",
      "topic": "校园学习&日常动作",
      "topic_en": "school",
      "level": "A",
      "sentence1": "Please **repeat** the word after the teacher.",
      "sentence1_cn": "请跟着老师重复这个单词。",
      "sentence2": "Can you **repeat** that sentence more slowly?",
      "sentence2_cn": "你能把那个句子说得慢一点吗？"
    },
    {
      "id": 38,
      "word": "share",
      "phonetic": "/ʃeə/",
      "part": "v.",
      "meaning": "分享",
      "topic": "校园学习&日常动作",
      "topic_en": "school",
      "level": "A",
      "sentence1": "Please **share** your ideas with the class.",
      "sentence1_cn": "请和全班分享你的想法。",
      "sentence2": "She **shared** her lunch with her best friend.",
      "sentence2_cn": "她和最好的朋友分享了午饭。"
    },
    {
      "id": 39,
      "word": "study",
      "phonetic": "/ˈstʌdi/",
      "part": "v.",
      "meaning": "学习，用功",
      "topic": "校园学习&日常动作",
      "topic_en": "school",
      "level": "A",
      "sentence1": "I **study** English for two hours every evening.",
      "sentence1_cn": "我每天晚上学习英语两个小时。",
      "sentence2": "She **studied** hard and passed all her exams.",
      "sentence2_cn": "她努力学习，通过了所有考试。"
    },
    {
      "id": 40,
      "word": "waste",
      "phonetic": "/weɪst/",
      "part": "v.",
      "meaning": "浪费",
      "topic": "校园学习&日常动作",
      "topic_en": "school",
      "level": "A",
      "sentence1": "Don't **waste** your time playing games all day.",
      "sentence1_cn": "不要整天玩游戏浪费时间。",
      "sentence2": "It is bad to **waste** food and water.",
      "sentence2_cn": "浪费食物和水是不好的。"
    },
    {
      "id": 41,
      "word": "afford",
      "phonetic": "/əˈfɔːd/",
      "part": "v.",
      "meaning": "买得起",
      "topic": "日常生活&饮食购物",
      "topic_en": "daily_life",
      "level": "B",
      "sentence1": "We cannot **afford** to buy a new computer now.",
      "sentence1_cn": "我们现在买不起新电脑。",
      "sentence2": "Can you **afford** the price of that jacket?",
      "sentence2_cn": "你买得起那件夹克吗？"
    },
    {
      "id": 42,
      "word": "bargain",
      "phonetic": "/ˈbɑːɡɪn/",
      "part": "n.",
      "meaning": "便宜货",
      "topic": "日常生活&饮食购物",
      "topic_en": "daily_life",
      "level": "B",
      "sentence1": "This coat was a real **bargain** – only ten pounds!",
      "sentence1_cn": "这件外套真是便宜货——只要十英镑！",
      "sentence2": "Mum loves to find a good **bargain** at the market.",
      "sentence2_cn": "妈妈喜欢在市场上找便宜货。"
    },
    {
      "id": 43,
      "word": "buy",
      "phonetic": "/baɪ/",
      "part": "v.",
      "meaning": "购买",
      "topic": "日常生活&饮食购物",
      "topic_en": "daily_life",
      "level": "B",
      "sentence1": "I want to **buy** a new book this weekend.",
      "sentence1_cn": "我这周末想买一本新书。",
      "sentence2": "She **bought** some fruit at the market yesterday.",
      "sentence2_cn": "她昨天在市场买了一些水果。"
    },
    {
      "id": 44,
      "word": "cheap",
      "phonetic": "/tʃiːp/",
      "part": "adj.",
      "meaning": "便宜的",
      "topic": "日常生活&饮食购物",
      "topic_en": "daily_life",
      "level": "B",
      "sentence1": "These shoes are very **cheap** and comfortable.",
      "sentence1_cn": "这些鞋子很便宜而且舒适。",
      "sentence2": "Is there a **cheap** restaurant near here?",
      "sentence2_cn": "这附近有便宜的餐厅吗？"
    },
    {
      "id": 45,
      "word": "choose",
      "phonetic": "/tʃuːz/",
      "part": "v.",
      "meaning": "选择",
      "topic": "日常生活&饮食购物",
      "topic_en": "daily_life",
      "level": "B",
      "sentence1": "Please **choose** a book from the shelf.",
      "sentence1_cn": "请从书架上选一本书。",
      "sentence2": "She **chose** the blue dress for the party.",
      "sentence2_cn": "她为派对选了蓝色连衣裙。"
    },
    {
      "id": 46,
      "word": "cost",
      "phonetic": "/kɒst/",
      "part": "v.",
      "meaning": "花费",
      "topic": "日常生活&饮食购物",
      "topic_en": "daily_life",
      "level": "B",
      "sentence1": "This book **costs** ten pounds.",
      "sentence1_cn": "这本书花了十英镑。",
      "sentence2": "How much does the ticket **cost**?",
      "sentence2_cn": "这张票多少钱？"
    },
    {
      "id": 47,
      "word": "delicious",
      "phonetic": "/dɪˈlɪʃəs/",
      "part": "adj.",
      "meaning": "美味的",
      "topic": "日常生活&饮食购物",
      "topic_en": "daily_life",
      "level": "B",
      "sentence1": "This cake is really **delicious**!",
      "sentence1_cn": "这个蛋糕真的太好吃了！",
      "sentence2": "Mum made a **delicious** soup for dinner.",
      "sentence2_cn": "妈妈做了一道美味的汤作为晚餐。"
    },
    {
      "id": 48,
      "word": "expensive",
      "phonetic": "/ɪkˈspensɪv/",
      "part": "adj.",
      "meaning": "昂贵的",
      "topic": "日常生活&饮食购物",
      "topic_en": "daily_life",
      "level": "B",
      "sentence1": "That coat is too **expensive** for me.",
      "sentence1_cn": "那件外套对我来说太贵了。",
      "sentence2": "Eating at that restaurant is very **expensive**.",
      "sentence2_cn": "在那家餐厅吃饭非常贵。"
    },
    {
      "id": 49,
      "word": "fresh",
      "phonetic": "/freʃ/",
      "part": "adj.",
      "meaning": "新鲜的",
      "topic": "日常生活&饮食购物",
      "topic_en": "daily_life",
      "level": "B",
      "sentence1": "I like to eat **fresh** fruit every morning.",
      "sentence1_cn": "我喜欢每天早上吃新鲜水果。",
      "sentence2": "The bread from the bakery is always **fresh**.",
      "sentence2_cn": "面包店的面包总是新鲜的。"
    },
    {
      "id": 50,
      "word": "hungry",
      "phonetic": "/ˈhʌŋɡri/",
      "part": "adj.",
      "meaning": "饥饿的",
      "topic": "日常生活&饮食购物",
      "topic_en": "daily_life",
      "level": "B",
      "sentence1": "I am very **hungry** after school.",
      "sentence1_cn": "放学后我非常饿。",
      "sentence2": "Are you **hungry**? Let's have a snack.",
      "sentence2_cn": "你饿了吗？我们来吃点零食吧。"
    },
    {
      "id": 51,
      "word": "menu",
      "phonetic": "/ˈmenjuː/",
      "part": "n.",
      "meaning": "菜单",
      "topic": "日常生活&饮食购物",
      "topic_en": "daily_life",
      "level": "B",
      "sentence1": "Could we see the **menu**, please?",
      "sentence1_cn": "请问我们可以看菜单吗？",
      "sentence2": "The **menu** at this café looks really good.",
      "sentence2_cn": "这家咖啡馆的菜单看起来很不错。"
    },
    {
      "id": 52,
      "word": "order",
      "phonetic": "/ˈɔːdə/",
      "part": "v.",
      "meaning": "点餐，订购",
      "topic": "日常生活&饮食购物",
      "topic_en": "daily_life",
      "level": "B",
      "sentence1": "I would like to **order** a sandwich, please.",
      "sentence1_cn": "我想点一个三明治，谢谢。",
      "sentence2": "She **ordered** a pizza and a glass of juice.",
      "sentence2_cn": "她点了一份披萨和一杯果汁。"
    },
    {
      "id": 53,
      "word": "price",
      "phonetic": "/praɪs/",
      "part": "n.",
      "meaning": "价格",
      "topic": "日常生活&饮食购物",
      "topic_en": "daily_life",
      "level": "B",
      "sentence1": "What is the **price** of this T-shirt?",
      "sentence1_cn": "这件T恤的价格是多少？",
      "sentence2": "The **price** of food is higher this year.",
      "sentence2_cn": "今年食品的价格更高了。"
    },
    {
      "id": 54,
      "word": "receive",
      "phonetic": "/rɪˈsiːv/",
      "part": "v.",
      "meaning": "收到",
      "topic": "日常生活&饮食购物",
      "topic_en": "daily_life",
      "level": "B",
      "sentence1": "I **received** a lovely birthday card from my friend.",
      "sentence1_cn": "我收到了朋友寄来的漂亮生日贺卡。",
      "sentence2": "She **received** a prize for her painting.",
      "sentence2_cn": "她因为她的画作获得了一个奖。"
    },
    {
      "id": 55,
      "word": "sell",
      "phonetic": "/sel/",
      "part": "v.",
      "meaning": "售卖",
      "topic": "日常生活&饮食购物",
      "topic_en": "daily_life",
      "level": "B",
      "sentence1": "This shop **sells** books and magazines.",
      "sentence1_cn": "这家店出售书籍和杂志。",
      "sentence2": "They **sold** all the cakes by lunchtime.",
      "sentence2_cn": "他们在午饭前就把蛋糕全部卖完了。"
    },
    {
      "id": 56,
      "word": "taste",
      "phonetic": "/teɪst/",
      "part": "v./n.",
      "meaning": "品尝/味道",
      "topic": "日常生活&饮食购物",
      "topic_en": "daily_life",
      "level": "B",
      "sentence1": "This soup **tastes** very good.",
      "sentence1_cn": "这道汤味道很好。",
      "sentence2": "**Taste** this apple – it is very sweet.",
      "sentence2_cn": "尝一尝这个苹果——它非常甜。"
    },
    {
      "id": 57,
      "word": "thirsty",
      "phonetic": "/ˈθɜːsti/",
      "part": "adj.",
      "meaning": "口渴的",
      "topic": "日常生活&饮食购物",
      "topic_en": "daily_life",
      "level": "B",
      "sentence1": "I am very **thirsty** after running.",
      "sentence1_cn": "跑步后我非常渴。",
      "sentence2": "Are you **thirsty**? Have some water.",
      "sentence2_cn": "你渴了吗？喝点水吧。"
    },
    {
      "id": 58,
      "word": "traditional",
      "phonetic": "/trəˈdɪʃənl/",
      "part": "adj.",
      "meaning": "传统的",
      "topic": "日常生活&饮食购物",
      "topic_en": "daily_life",
      "level": "B",
      "sentence1": "We eat **traditional** food at New Year.",
      "sentence1_cn": "我们在新年吃传统食物。",
      "sentence2": "She wore a **traditional** dress at the festival.",
      "sentence2_cn": "她在节日上穿了一件传统服装。"
    },
    {
      "id": 59,
      "word": "value",
      "phonetic": "/ˈvæljuː/",
      "part": "n.",
      "meaning": "价值",
      "topic": "日常生活&饮食购物",
      "topic_en": "daily_life",
      "level": "B",
      "sentence1": "This bag is good **value** for money.",
      "sentence1_cn": "这个包物有所值。",
      "sentence2": "Family is the most important **value** in life.",
      "sentence2_cn": "家庭是生活中最重要的价值。"
    },
    {
      "id": 60,
      "word": "airport",
      "phonetic": "/ˈeəpɔːt/",
      "part": "n.",
      "meaning": "机场",
      "topic": "出行旅游&环境天气",
      "topic_en": "travel",
      "level": "B",
      "sentence1": "We arrived at the **airport** two hours early.",
      "sentence1_cn": "我们提前两小时到达了机场。",
      "sentence2": "The **airport** is far from the city centre.",
      "sentence2_cn": "机场离市中心很远。"
    },
    {
      "id": 61,
      "word": "arrive",
      "phonetic": "/əˈraɪv/",
      "part": "v.",
      "meaning": "到达",
      "topic": "出行旅游&环境天气",
      "topic_en": "travel",
      "level": "B",
      "sentence1": "What time does the train **arrive** in London?",
      "sentence1_cn": "火车几点到达伦敦？",
      "sentence2": "She **arrived** at school ten minutes late.",
      "sentence2_cn": "她上学迟到了十分钟。"
    },
    {
      "id": 62,
      "word": "bridge",
      "phonetic": "/brɪdʒ/",
      "part": "n.",
      "meaning": "桥",
      "topic": "出行旅游&环境天气",
      "topic_en": "travel",
      "level": "B",
      "sentence1": "We walked across a long **bridge** over the river.",
      "sentence1_cn": "我们走过了一座横跨河流的长桥。",
      "sentence2": "There is an old **bridge** near our village.",
      "sentence2_cn": "我们村附近有一座古老的桥。"
    },
    {
      "id": 63,
      "word": "countryside",
      "phonetic": "/ˈkʌntrisaɪd/",
      "part": "n.",
      "meaning": "乡村",
      "topic": "出行旅游&环境天气",
      "topic_en": "travel",
      "level": "B",
      "sentence1": "I love walking in the **countryside** at weekends.",
      "sentence1_cn": "我喜欢在周末去乡村散步。",
      "sentence2": "The **countryside** is quiet and very beautiful.",
      "sentence2_cn": "乡村很安静，非常美丽。"
    },
    {
      "id": 64,
      "word": "direction",
      "phonetic": "/dɪˈrekʃn/",
      "part": "n.",
      "meaning": "方向",
      "topic": "出行旅游&环境天气",
      "topic_en": "travel",
      "level": "B",
      "sentence1": "Can you tell me the **direction** to the station?",
      "sentence1_cn": "你能告诉我去车站的方向吗？",
      "sentence2": "We followed the **direction** on the map.",
      "sentence2_cn": "我们按照地图上的方向走。"
    },
    {
      "id": 65,
      "word": "forest",
      "phonetic": "/ˈfɒrɪst/",
      "part": "n.",
      "meaning": "森林",
      "topic": "出行旅游&环境天气",
      "topic_en": "travel",
      "level": "B",
      "sentence1": "We saw many animals in the **forest**.",
      "sentence1_cn": "我们在森林里看到了许多动物。",
      "sentence2": "The **forest** near our town is very old.",
      "sentence2_cn": "我们镇附近的森林非常古老。"
    },
    {
      "id": 66,
      "word": "journey",
      "phonetic": "/ˈdʒɜːni/",
      "part": "n.",
      "meaning": "旅途，旅行",
      "topic": "出行旅游&环境天气",
      "topic_en": "travel",
      "level": "B",
      "sentence1": "The **journey** from London to Paris takes two hours.",
      "sentence1_cn": "从伦敦到巴黎的旅程需要两个小时。",
      "sentence2": "We had a long **journey** by train to the coast.",
      "sentence2_cn": "我们乘火车去海边进行了漫长的旅程。"
    },
    {
      "id": 67,
      "word": "leave",
      "phonetic": "/liːv/",
      "part": "v.",
      "meaning": "离开，出发",
      "topic": "出行旅游&环境天气",
      "topic_en": "travel",
      "level": "B",
      "sentence1": "The bus **leaves** at half past eight.",
      "sentence1_cn": "公共汽车八点半出发。",
      "sentence2": "We **left** home early to catch the train.",
      "sentence2_cn": "我们早早离开家去赶火车。"
    },
    {
      "id": 68,
      "word": "mountain",
      "phonetic": "/ˈmaʊntɪn/",
      "part": "n.",
      "meaning": "山",
      "topic": "出行旅游&环境天气",
      "topic_en": "travel",
      "level": "B",
      "sentence1": "We went hiking in the **mountains** last summer.",
      "sentence1_cn": "去年夏天我们去山里徒步。",
      "sentence2": "The **mountain** is covered with snow in winter.",
      "sentence2_cn": "冬天这座山被雪覆盖着。"
    },
    {
      "id": 69,
      "word": "path",
      "phonetic": "/pɑːθ/",
      "part": "n.",
      "meaning": "小路",
      "topic": "出行旅游&环境天气",
      "topic_en": "travel",
      "level": "B",
      "sentence1": "Follow the **path** through the park.",
      "sentence1_cn": "沿着穿过公园的小路走。",
      "sentence2": "There is a narrow **path** along the river.",
      "sentence2_cn": "沿着河边有一条狭窄的小路。"
    },
    {
      "id": 70,
      "word": "railway",
      "phonetic": "/ˈreɪlweɪ/",
      "part": "n.",
      "meaning": "铁路",
      "topic": "出行旅游&环境天气",
      "topic_en": "travel",
      "level": "B",
      "sentence1": "The **railway** station is ten minutes away.",
      "sentence1_cn": "火车站距离这里十分钟。",
      "sentence2": "We crossed the **railway** bridge on our walk.",
      "sentence2_cn": "我们散步时穿越了铁路桥。"
    },
    {
      "id": 71,
      "word": "route",
      "phonetic": "/ruːt/",
      "part": "n.",
      "meaning": "路线",
      "topic": "出行旅游&环境天气",
      "topic_en": "travel",
      "level": "B",
      "sentence1": "This is the fastest **route** to the school.",
      "sentence1_cn": "这是去学校最快的路线。",
      "sentence2": "We planned our **route** on a map before the trip.",
      "sentence2_cn": "旅行前我们在地图上规划了路线。"
    },
    {
      "id": 72,
      "word": "station",
      "phonetic": "/ˈsteɪʃn/",
      "part": "n.",
      "meaning": "车站",
      "topic": "出行旅游&环境天气",
      "topic_en": "travel",
      "level": "B",
      "sentence1": "Meet me at the bus **station** at three o'clock.",
      "sentence1_cn": "三点钟在公共汽车站见我。",
      "sentence2": "The train **station** is very busy on Mondays.",
      "sentence2_cn": "火车站在周一非常繁忙。"
    },
    {
      "id": 73,
      "word": "storm",
      "phonetic": "/stɔːm/",
      "part": "n.",
      "meaning": "暴风雨",
      "topic": "出行旅游&环境天气",
      "topic_en": "travel",
      "level": "B",
      "sentence1": "There was a big **storm** last night.",
      "sentence1_cn": "昨晚有一场大暴风雨。",
      "sentence2": "The **storm** made it impossible to go outside.",
      "sentence2_cn": "暴风雨使得我们无法外出。"
    },
    {
      "id": 74,
      "word": "tourist",
      "phonetic": "/ˈtʊərɪst/",
      "part": "n.",
      "meaning": "游客",
      "topic": "出行旅游&环境天气",
      "topic_en": "travel",
      "level": "B",
      "sentence1": "Many **tourists** visit the castle every year.",
      "sentence1_cn": "每年有许多游客参观这座城堡。",
      "sentence2": "The **tourist** map shows all the main sights.",
      "sentence2_cn": "游客地图显示了所有主要景点。"
    },
    {
      "id": 75,
      "word": "traffic",
      "phonetic": "/ˈtræfɪk/",
      "part": "n.",
      "meaning": "交通",
      "topic": "出行旅游&环境天气",
      "topic_en": "travel",
      "level": "B",
      "sentence1": "There is a lot of **traffic** in the city centre.",
      "sentence1_cn": "市中心有很多交通拥挤。",
      "sentence2": "The bus was late because of heavy **traffic**.",
      "sentence2_cn": "公共汽车因为交通拥堵而晚点了。"
    },
    {
      "id": 76,
      "word": "travel",
      "phonetic": "/ˈtrævl/",
      "part": "v.",
      "meaning": "旅行",
      "topic": "出行旅游&环境天气",
      "topic_en": "travel",
      "level": "B",
      "sentence1": "I would love to **travel** around the world.",
      "sentence1_cn": "我很想环游世界。",
      "sentence2": "We **travelled** by train to visit our grandparents.",
      "sentence2_cn": "我们乘火车去看望祖父母。"
    },
    {
      "id": 77,
      "word": "weather",
      "phonetic": "/ˈweðə/",
      "part": "n.",
      "meaning": "天气",
      "topic": "出行旅游&环境天气",
      "topic_en": "travel",
      "level": "B",
      "sentence1": "What is the **weather** like today?",
      "sentence1_cn": "今天天气怎么样？",
      "sentence2": "The **weather** was warm and sunny during our holiday.",
      "sentence2_cn": "假期期间天气温暖而晴朗。"
    },
    {
      "id": 78,
      "word": "wind",
      "phonetic": "/wɪnd/",
      "part": "n.",
      "meaning": "风",
      "topic": "出行旅游&环境天气",
      "topic_en": "travel",
      "level": "B",
      "sentence1": "The **wind** is very strong today.",
      "sentence1_cn": "今天风很大。",
      "sentence2": "A cold **wind** blew across the playground.",
      "sentence2_cn": "一阵冷风吹过操场。"
    },
    {
      "id": 79,
      "word": "windy",
      "phonetic": "/ˈwɪndi/",
      "part": "adj.",
      "meaning": "刮风的",
      "topic": "出行旅游&环境天气",
      "topic_en": "travel",
      "level": "B",
      "sentence1": "It is very **windy** today – hold your hat!",
      "sentence1_cn": "今天风很大——抓住你的帽子！",
      "sentence2": "We could not fly our kite because it was too **windy**.",
      "sentence2_cn": "因为风太大，我们无法放风筝。"
    },
    {
      "id": 80,
      "word": "activity",
      "phonetic": "/ækˈtɪvɪti/",
      "part": "n.",
      "meaning": "活动",
      "topic": "兴趣爱好&健康情绪",
      "topic_en": "hobbies",
      "level": "B",
      "sentence1": "Swimming is my favourite after-school **activity**.",
      "sentence1_cn": "游泳是我最喜欢的课外活动。",
      "sentence2": "The school has many **activities** for students.",
      "sentence2_cn": "学校为学生提供很多活动。"
    },
    {
      "id": 81,
      "word": "artist",
      "phonetic": "/ˈɑːtɪst/",
      "part": "n.",
      "meaning": "艺术家，画家",
      "topic": "兴趣爱好&健康情绪",
      "topic_en": "hobbies",
      "level": "B",
      "sentence1": "She wants to be an **artist** when she grows up.",
      "sentence1_cn": "她长大后想成为一名艺术家。",
      "sentence2": "The **artist** painted a beautiful picture of the sea.",
      "sentence2_cn": "这位艺术家画了一幅美丽的海景画。"
    },
    {
      "id": 82,
      "word": "celebrate",
      "phonetic": "/ˈselɪbreɪt/",
      "part": "v.",
      "meaning": "庆祝",
      "topic": "兴趣爱好&健康情绪",
      "topic_en": "hobbies",
      "level": "B",
      "sentence1": "We **celebrate** birthdays with a cake and songs.",
      "sentence1_cn": "我们用蛋糕和歌曲庆祝生日。",
      "sentence2": "They **celebrated** the New Year with fireworks.",
      "sentence2_cn": "他们用烟火庆祝新年。"
    },
    {
      "id": 83,
      "word": "concert",
      "phonetic": "/ˈkɒnsət/",
      "part": "n.",
      "meaning": "音乐会",
      "topic": "兴趣爱好&健康情绪",
      "topic_en": "hobbies",
      "level": "B",
      "sentence1": "We went to a music **concert** last Saturday.",
      "sentence1_cn": "上周六我们去看了一场音乐会。",
      "sentence2": "The school **concert** was really wonderful.",
      "sentence2_cn": "学校音乐会真的非常精彩。"
    },
    {
      "id": 84,
      "word": "dance",
      "phonetic": "/dɑːns/",
      "part": "v.",
      "meaning": "跳舞",
      "topic": "兴趣爱好&健康情绪",
      "topic_en": "hobbies",
      "level": "B",
      "sentence1": "I love to **dance** to pop music.",
      "sentence1_cn": "我喜欢随着流行音乐跳舞。",
      "sentence2": "She **danced** at the school show last week.",
      "sentence2_cn": "她上周在学校演出中跳舞了。"
    },
    {
      "id": 85,
      "word": "exercise",
      "phonetic": "/ˈeksəsaɪz/",
      "part": "n./v.",
      "meaning": "锻炼",
      "topic": "兴趣爱好&健康情绪",
      "topic_en": "hobbies",
      "level": "B",
      "sentence1": "**Exercise** is very important for good health.",
      "sentence1_cn": "锻炼对健康非常重要。",
      "sentence2": "She **exercises** every morning before school.",
      "sentence2_cn": "她每天早上上学前锻炼。"
    },
    {
      "id": 86,
      "word": "festival",
      "phonetic": "/ˈfestɪvl/",
      "part": "n.",
      "meaning": "节日",
      "topic": "兴趣爱好&健康情绪",
      "topic_en": "hobbies",
      "level": "B",
      "sentence1": "My favourite **festival** is the Spring Festival.",
      "sentence1_cn": "我最喜欢的节日是春节。",
      "sentence2": "There is a music **festival** in our town every summer.",
      "sentence2_cn": "我们镇每年夏天都有音乐节。"
    },
    {
      "id": 87,
      "word": "hobby",
      "phonetic": "/ˈhɒbi/",
      "part": "n.",
      "meaning": "爱好",
      "topic": "兴趣爱好&健康情绪",
      "topic_en": "hobbies",
      "level": "B",
      "sentence1": "My **hobby** is collecting stamps and postcards.",
      "sentence1_cn": "我的爱好是收集邮票和明信片。",
      "sentence2": "What is your favourite **hobby** after school?",
      "sentence2_cn": "你课后最喜欢的爱好是什么？"
    },
    {
      "id": 88,
      "word": "healthy",
      "phonetic": "/ˈhelθi/",
      "part": "adj.",
      "meaning": "健康的",
      "topic": "兴趣爱好&健康情绪",
      "topic_en": "hobbies",
      "level": "B",
      "sentence1": "Eating fruit and vegetables keeps you **healthy**.",
      "sentence1_cn": "吃水果和蔬菜能让你保持健康。",
      "sentence2": "She lives a **healthy** life and goes running every day.",
      "sentence2_cn": "她过着健康的生活，每天跑步。"
    },
    {
      "id": 89,
      "word": "interested",
      "phonetic": "/ˈɪntrəstɪd/",
      "part": "adj.",
      "meaning": "感兴趣的",
      "topic": "兴趣爱好&健康情绪",
      "topic_en": "hobbies",
      "level": "B",
      "sentence1": "I am very **interested** in learning about animals.",
      "sentence1_cn": "我对学习动物知识非常感兴趣。",
      "sentence2": "Are you **interested** in joining the art club?",
      "sentence2_cn": "你有兴趣加入美术俱乐部吗？"
    },
    {
      "id": 90,
      "word": "match",
      "phonetic": "/mætʃ/",
      "part": "n.",
      "meaning": "比赛",
      "topic": "兴趣爱好&健康情绪",
      "topic_en": "hobbies",
      "level": "B",
      "sentence1": "We watched a football **match** on Saturday.",
      "sentence1_cn": "我们星期六看了一场足球比赛。",
      "sentence2": "Our school won the basketball **match** yesterday.",
      "sentence2_cn": "我们学校昨天赢了篮球比赛。"
    },
    {
      "id": 91,
      "word": "music",
      "phonetic": "/ˈmjuːzɪk/",
      "part": "n.",
      "meaning": "音乐",
      "topic": "兴趣爱好&健康情绪",
      "topic_en": "hobbies",
      "level": "B",
      "sentence1": "I listen to **music** every evening before bed.",
      "sentence1_cn": "我每晚睡前听音乐。",
      "sentence2": "She plays **music** and dances at the school show.",
      "sentence2_cn": "她在学校演出中演奏音乐并跳舞。"
    },
    {
      "id": 92,
      "word": "relax",
      "phonetic": "/rɪˈlæks/",
      "part": "v.",
      "meaning": "放松",
      "topic": "兴趣爱好&健康情绪",
      "topic_en": "hobbies",
      "level": "B",
      "sentence1": "I like to **relax** by reading after school.",
      "sentence1_cn": "我喜欢放学后通过读书来放松。",
      "sentence2": "**Relax** and take a deep breath before the test.",
      "sentence2_cn": "考试前放松一下，深呼吸。"
    },
    {
      "id": 93,
      "word": "sport",
      "phonetic": "/spɔːt/",
      "part": "n.",
      "meaning": "运动",
      "topic": "兴趣爱好&健康情绪",
      "topic_en": "hobbies",
      "level": "B",
      "sentence1": "My favourite **sport** is swimming.",
      "sentence1_cn": "我最喜欢的运动是游泳。",
      "sentence2": "She plays **sport** every day to stay fit.",
      "sentence2_cn": "她每天运动以保持健康。"
    },
    {
      "id": 94,
      "word": "talent",
      "phonetic": "/ˈtælənt/",
      "part": "n.",
      "meaning": "天赋",
      "topic": "兴趣爱好&健康情绪",
      "topic_en": "hobbies",
      "level": "B",
      "sentence1": "She has a great **talent** for singing.",
      "sentence1_cn": "她有很高的唱歌天赋。",
      "sentence2": "Everyone has a special **talent** of their own.",
      "sentence2_cn": "每个人都有自己特别的天赋。"
    },
    {
      "id": 95,
      "word": "tired",
      "phonetic": "/ˈtaɪəd/",
      "part": "adj.",
      "meaning": "疲惫的",
      "topic": "兴趣爱好&健康情绪",
      "topic_en": "hobbies",
      "level": "B",
      "sentence1": "I feel very **tired** after my swimming lesson.",
      "sentence1_cn": "游泳课后我感到非常疲惫。",
      "sentence2": "She was **tired** but still finished her homework.",
      "sentence2_cn": "她虽然很累，但还是完成了作业。"
    },
    {
      "id": 96,
      "word": "volunteer",
      "phonetic": "/ˌvɒlənˈtɪə/",
      "part": "n.",
      "meaning": "志愿者",
      "topic": "兴趣爱好&健康情绪",
      "topic_en": "hobbies",
      "level": "B",
      "sentence1": "She is a **volunteer** at the local library.",
      "sentence1_cn": "她是当地图书馆的志愿者。",
      "sentence2": "Many **volunteers** helped clean the park.",
      "sentence2_cn": "许多志愿者帮助清洁公园。"
    },
    {
      "id": 97,
      "word": "win",
      "phonetic": "/wɪn/",
      "part": "v.",
      "meaning": "赢得，获胜",
      "topic": "兴趣爱好&健康情绪",
      "topic_en": "hobbies",
      "level": "B",
      "sentence1": "Our team **won** the football match last weekend.",
      "sentence1_cn": "我们队上周末赢了足球比赛。",
      "sentence2": "She **won** first prize in the art competition.",
      "sentence2_cn": "她在美术比赛中获得了一等奖。"
    },
    {
      "id": 98,
      "word": "wonderful",
      "phonetic": "/ˈwʌndəfl/",
      "part": "adj.",
      "meaning": "极好的",
      "topic": "兴趣爱好&健康情绪",
      "topic_en": "hobbies",
      "level": "B",
      "sentence1": "We had a **wonderful** time at the festival.",
      "sentence1_cn": "我们在节日上度过了美好的时光。",
      "sentence2": "What a **wonderful** surprise to see you here!",
      "sentence2_cn": "在这里见到你真是太惊喜了！"
    },
    {
      "id": 99,
      "word": "alone",
      "phonetic": "/əˈləʊn/",
      "part": "adj.",
      "meaning": "独自的，单独的",
      "topic": "人物&状态",
      "topic_en": "states",
      "level": "B",
      "sentence1": "She sat **alone** in the classroom after school.",
      "sentence1_cn": "放学后她独自坐在教室里。",
      "sentence2": "I don't like going to the cinema **alone**.",
      "sentence2_cn": "我不喜欢独自去电影院。"
    },
    {
      "id": 100,
      "word": "angry",
      "phonetic": "/ˈæŋɡri/",
      "part": "adj.",
      "meaning": "生气的",
      "topic": "人物&状态",
      "topic_en": "states",
      "level": "B",
      "sentence1": "My dad was **angry** when I came home late.",
      "sentence1_cn": "我回家晚了，爸爸很生气。",
      "sentence2": "She was **angry** because I lost her book.",
      "sentence2_cn": "她很生气，因为我弄丢了她的书。"
    },
    {
      "id": 101,
      "word": "beautiful",
      "phonetic": "/ˈbjuːtɪfl/",
      "part": "adj.",
      "meaning": "美丽的，漂亮的",
      "topic": "人物&状态",
      "topic_en": "states",
      "level": "B",
      "sentence1": "She wore a **beautiful** dress to the party.",
      "sentence1_cn": "她穿了一件漂亮的裙子去派对。",
      "sentence2": "The flowers in the garden are **beautiful** in spring.",
      "sentence2_cn": "花园里的花在春天很美丽。"
    },
    {
      "id": 102,
      "word": "bored",
      "phonetic": "/bɔːd/",
      "part": "adj.",
      "meaning": "无聊的",
      "topic": "人物&状态",
      "topic_en": "states",
      "level": "B",
      "sentence1": "I felt **bored** because there was nothing to do.",
      "sentence1_cn": "我感到无聊，因为没有什么事情可做。",
      "sentence2": "She was **bored** at home during the holidays.",
      "sentence2_cn": "假期在家时她感到无聊。"
    },
    {
      "id": 103,
      "word": "bright",
      "phonetic": "/braɪt/",
      "part": "adj.",
      "meaning": "明亮的，聪明的",
      "topic": "人物&状态",
      "topic_en": "states",
      "level": "B",
      "sentence1": "The sun is very **bright** this morning.",
      "sentence1_cn": "今天早上阳光非常明亮。",
      "sentence2": "She is a **bright** student who loves reading.",
      "sentence2_cn": "她是一个聪明的学生，喜欢读书。"
    },
    {
      "id": 104,
      "word": "clean",
      "phonetic": "/kliːn/",
      "part": "adj./v.",
      "meaning": "干净的/打扫",
      "topic": "人物&状态",
      "topic_en": "states",
      "level": "B",
      "sentence1": "Please keep your desk **clean** and tidy.",
      "sentence1_cn": "请保持你的桌子干净整洁。",
      "sentence2": "We **cleaned** the classroom before going home.",
      "sentence2_cn": "我们回家前打扫了教室。"
    },
    {
      "id": 105,
      "word": "cold",
      "phonetic": "/kəʊld/",
      "part": "adj.",
      "meaning": "寒冷的",
      "topic": "人物&状态",
      "topic_en": "states",
      "level": "B",
      "sentence1": "It is very **cold** outside today.",
      "sentence1_cn": "今天外面非常寒冷。",
      "sentence2": "Put on a coat because it is **cold**.",
      "sentence2_cn": "穿上外套，因为天气很冷。"
    },
    {
      "id": 106,
      "word": "cool",
      "phonetic": "/kuːl/",
      "part": "adj.",
      "meaning": "凉爽的，酷的",
      "topic": "人物&状态",
      "topic_en": "states",
      "level": "B",
      "sentence1": "The weather is nice and **cool** in autumn.",
      "sentence1_cn": "秋天天气凉爽宜人。",
      "sentence2": "That is a really **cool** bike!",
      "sentence2_cn": "那辆自行车真的很酷！"
    },
    {
      "id": 107,
      "word": "dangerous",
      "phonetic": "/ˈdeɪndʒərəs/",
      "part": "adj.",
      "meaning": "危险的",
      "topic": "人物&状态",
      "topic_en": "states",
      "level": "B",
      "sentence1": "It is **dangerous** to run near the swimming pool.",
      "sentence1_cn": "在游泳池附近跑步是危险的。",
      "sentence2": "Swimming in the sea alone can be **dangerous**.",
      "sentence2_cn": "独自在海里游泳可能很危险。"
    },
    {
      "id": 108,
      "word": "dark",
      "phonetic": "/dɑːk/",
      "part": "adj.",
      "meaning": "黑暗的",
      "topic": "人物&状态",
      "topic_en": "states",
      "level": "B",
      "sentence1": "It is very **dark** outside at night.",
      "sentence1_cn": "夜里外面非常黑暗。",
      "sentence2": "She is afraid of the **dark** and uses a night light.",
      "sentence2_cn": "她怕黑，所以用夜灯。"
    },
    {
      "id": 109,
      "word": "different",
      "phonetic": "/ˈdɪfrənt/",
      "part": "adj.",
      "meaning": "不同的",
      "topic": "人物&状态",
      "topic_en": "states",
      "level": "B",
      "sentence1": "My sister and I have very **different** hobbies.",
      "sentence1_cn": "我和姐姐有非常不同的爱好。",
      "sentence2": "These two books are **different** from each other.",
      "sentence2_cn": "这两本书彼此不同。"
    },
    {
      "id": 110,
      "word": "difficult",
      "phonetic": "/ˈdɪfɪkəlt/",
      "part": "adj.",
      "meaning": "困难的",
      "topic": "人物&状态",
      "topic_en": "states",
      "level": "B",
      "sentence1": "The maths test was very **difficult** today.",
      "sentence1_cn": "今天的数学考试非常难。",
      "sentence2": "Learning a new language can be **difficult** at first.",
      "sentence2_cn": "学习一门新语言起初可能很困难。"
    },
    {
      "id": 111,
      "word": "dirty",
      "phonetic": "/ˈdɜːti/",
      "part": "adj.",
      "meaning": "脏的",
      "topic": "人物&状态",
      "topic_en": "states",
      "level": "B",
      "sentence1": "My shoes are very **dirty** after playing outside.",
      "sentence1_cn": "在外面玩耍后我的鞋子很脏。",
      "sentence2": "Please wash your hands because they are **dirty**.",
      "sentence2_cn": "请洗手，因为你的手很脏。"
    },
    {
      "id": 112,
      "word": "easy",
      "phonetic": "/ˈiːzi/",
      "part": "adj.",
      "meaning": "容易的",
      "topic": "人物&状态",
      "topic_en": "states",
      "level": "B",
      "sentence1": "The first question in the test was very **easy**.",
      "sentence1_cn": "考试中的第一道题非常容易。",
      "sentence2": "This recipe is very **easy** to follow.",
      "sentence2_cn": "这个食谱非常容易跟着做。"
    },
    {
      "id": 113,
      "word": "excited",
      "phonetic": "/ɪkˈsaɪtɪd/",
      "part": "adj.",
      "meaning": "兴奋的",
      "topic": "人物&状态",
      "topic_en": "states",
      "level": "B",
      "sentence1": "I am very **excited** about my birthday party.",
      "sentence1_cn": "我对生日派对非常兴奋。",
      "sentence2": "She was **excited** when she heard the good news.",
      "sentence2_cn": "当她听到好消息时非常兴奋。"
    },
    {
      "id": 114,
      "word": "famous",
      "phonetic": "/ˈfeɪməs/",
      "part": "adj.",
      "meaning": "著名的",
      "topic": "人物&状态",
      "topic_en": "states",
      "level": "B",
      "sentence1": "Paris is **famous** for its beautiful buildings.",
      "sentence1_cn": "巴黎以其美丽的建筑而闻名。",
      "sentence2": "She is a **famous** singer all over the world.",
      "sentence2_cn": "她是全球知名的歌手。"
    },
    {
      "id": 115,
      "word": "fast",
      "phonetic": "/fɑːst/",
      "part": "adj./adv.",
      "meaning": "快的，快速地",
      "topic": "人物&状态",
      "topic_en": "states",
      "level": "B",
      "sentence1": "She is the **fastest** runner in our class.",
      "sentence1_cn": "她是我们班跑得最快的。",
      "sentence2": "The car drove very **fast** on the motorway.",
      "sentence2_cn": "汽车在高速公路上开得很快。"
    },
    {
      "id": 116,
      "word": "fat",
      "phonetic": "/fæt/",
      "part": "adj.",
      "meaning": "胖的，肥的",
      "topic": "人物&状态",
      "topic_en": "states",
      "level": "B",
      "sentence1": "The **fat** cat sat on the warm sofa.",
      "sentence1_cn": "那只胖猫坐在温暖的沙发上。",
      "sentence2": "Eating too much sugar can make you **fat**.",
      "sentence2_cn": "吃太多糖会让你变胖。"
    },
    {
      "id": 117,
      "word": "fit",
      "phonetic": "/fɪt/",
      "part": "adj.",
      "meaning": "健康的，合适的",
      "topic": "人物&状态",
      "topic_en": "states",
      "level": "B",
      "sentence1": "She goes running every day to stay **fit**.",
      "sentence1_cn": "她每天跑步以保持健康。",
      "sentence2": "You need to get **fit** before the swimming race.",
      "sentence2_cn": "你需要在游泳比赛前保持健康。"
    },
    {
      "id": 118,
      "word": "funny",
      "phonetic": "/ˈfʌni/",
      "part": "adj.",
      "meaning": "有趣的，滑稽的",
      "topic": "人物&状态",
      "topic_en": "states",
      "level": "B",
      "sentence1": "My dad always tells **funny** jokes at dinner.",
      "sentence1_cn": "我爸爸总是在晚饭时讲有趣的笑话。",
      "sentence2": "The cartoon was very **funny** and we all laughed.",
      "sentence2_cn": "这部卡通片非常有趣，我们都笑了。"
    },
    {
      "id": 119,
      "word": "add",
      "phonetic": "/æd/",
      "part": "v.",
      "meaning": "添加，增加",
      "topic": "学习&工作动作",
      "topic_en": "study_work",
      "level": "B",
      "sentence1": "**Add** some salt to the soup, please.",
      "sentence1_cn": "请往汤里加点盐。",
      "sentence2": "She **added** her name to the list.",
      "sentence2_cn": "她把名字加到了名单上。"
    },
    {
      "id": 120,
      "word": "allow",
      "phonetic": "/əˈlaʊ/",
      "part": "v.",
      "meaning": "允许",
      "topic": "学习&工作动作",
      "topic_en": "study_work",
      "level": "B",
      "sentence1": "We are not **allowed** to use phones in class.",
      "sentence1_cn": "我们在课堂上不允许使用手机。",
      "sentence2": "My parents **allow** me to watch TV for one hour.",
      "sentence2_cn": "我父母允许我看一小时电视。"
    },
    {
      "id": 121,
      "word": "answer",
      "phonetic": "/ˈɑːnsə/",
      "part": "v.",
      "meaning": "回答",
      "topic": "学习&工作动作",
      "topic_en": "study_work",
      "level": "B",
      "sentence1": "Please **answer** all the questions in the test.",
      "sentence1_cn": "请回答考试中的所有问题。",
      "sentence2": "She **answered** the teacher's question correctly.",
      "sentence2_cn": "她正确回答了老师的问题。"
    },
    {
      "id": 122,
      "word": "ask",
      "phonetic": "/ɑːsk/",
      "part": "v.",
      "meaning": "询问，要求",
      "topic": "学习&工作动作",
      "topic_en": "study_work",
      "level": "B",
      "sentence1": "You can **ask** the teacher if you do not understand.",
      "sentence1_cn": "如果你不明白，可以问老师。",
      "sentence2": "She **asked** her friend for help with the homework.",
      "sentence2_cn": "她请朋友帮助做作业。"
    },
    {
      "id": 123,
      "word": "believe",
      "phonetic": "/bɪˈliːv/",
      "part": "v.",
      "meaning": "相信",
      "topic": "学习&工作动作",
      "topic_en": "study_work",
      "level": "B",
      "sentence1": "I **believe** you can pass the KET exam.",
      "sentence1_cn": "我相信你能通过KET考试。",
      "sentence2": "Do you **believe** this story is true?",
      "sentence2_cn": "你相信这个故事是真的吗？"
    },
    {
      "id": 124,
      "word": "break",
      "phonetic": "/breɪk/",
      "part": "v.",
      "meaning": "打破，弄坏",
      "topic": "学习&工作动作",
      "topic_en": "study_work",
      "level": "B",
      "sentence1": "Be careful! Don't **break** the glasses.",
      "sentence1_cn": "小心！不要打破玻璃杯。",
      "sentence2": "She **broke** her arm when she fell off her bike.",
      "sentence2_cn": "她从自行车上摔下来，摔断了手臂。"
    },
    {
      "id": 125,
      "word": "bring",
      "phonetic": "/brɪŋ/",
      "part": "v.",
      "meaning": "带来，拿来",
      "topic": "学习&工作动作",
      "topic_en": "study_work",
      "level": "B",
      "sentence1": "Please **bring** your book to class tomorrow.",
      "sentence1_cn": "请明天把你的书带到课上。",
      "sentence2": "She **brought** some cakes to share with the class.",
      "sentence2_cn": "她带了一些蛋糕和全班同学分享。"
    },
    {
      "id": 126,
      "word": "build",
      "phonetic": "/bɪld/",
      "part": "v.",
      "meaning": "建造，搭建",
      "topic": "学习&工作动作",
      "topic_en": "study_work",
      "level": "B",
      "sentence1": "We **built** a sandcastle on the beach.",
      "sentence1_cn": "我们在海滩上建造了一座沙堡。",
      "sentence2": "He wants to **build** a treehouse in the garden.",
      "sentence2_cn": "他想在花园里搭建一个树屋。"
    },
    {
      "id": 127,
      "word": "call",
      "phonetic": "/kɔːl/",
      "part": "v.",
      "meaning": "称呼，打电话",
      "topic": "学习&工作动作",
      "topic_en": "study_work",
      "level": "B",
      "sentence1": "She **called** her grandmother every Sunday.",
      "sentence1_cn": "她每个星期天给祖母打电话。",
      "sentence2": "What do you **call** this animal in English?",
      "sentence2_cn": "这种动物用英语怎么称呼？"
    },
    {
      "id": 128,
      "word": "carry",
      "phonetic": "/ˈkæri/",
      "part": "v.",
      "meaning": "携带，搬运",
      "topic": "学习&工作动作",
      "topic_en": "study_work",
      "level": "B",
      "sentence1": "Can you **carry** this heavy bag for me?",
      "sentence1_cn": "你能帮我搬这个重包吗？",
      "sentence2": "She **carried** her lunch in a small bag.",
      "sentence2_cn": "她用一个小包带着她的午饭。"
    },
    {
      "id": 129,
      "word": "catch",
      "phonetic": "/kætʃ/",
      "part": "v.",
      "meaning": "抓住，接住",
      "topic": "学习&工作动作",
      "topic_en": "study_work",
      "level": "B",
      "sentence1": "She **caught** the ball and threw it back.",
      "sentence1_cn": "她接住球后又把球扔了回去。",
      "sentence2": "Hurry up or you will miss the bus – we have to **catch** it!",
      "sentence2_cn": "快点，不然你会错过公共汽车的，我们得赶上它！"
    },
    {
      "id": 130,
      "word": "change",
      "phonetic": "/tʃeɪndʒ/",
      "part": "v.",
      "meaning": "改变，更换",
      "topic": "学习&工作动作",
      "topic_en": "study_work",
      "level": "B",
      "sentence1": "I will **change** my clothes after school.",
      "sentence1_cn": "我放学后会换衣服。",
      "sentence2": "The weather can **change** very quickly in spring.",
      "sentence2_cn": "春天天气变化很快。"
    },
    {
      "id": 131,
      "word": "check",
      "phonetic": "/tʃek/",
      "part": "v.",
      "meaning": "检查，核对",
      "topic": "学习&工作动作",
      "topic_en": "study_work",
      "level": "B",
      "sentence1": "Please **check** your answers before handing in the test.",
      "sentence1_cn": "交卷前请检查你的答案。",
      "sentence2": "She **checked** her bag to make sure she had her keys.",
      "sentence2_cn": "她检查了包以确保带了钥匙。"
    },
    {
      "id": 132,
      "word": "close",
      "phonetic": "/kləʊz/",
      "part": "v.",
      "meaning": "关闭",
      "topic": "学习&工作动作",
      "topic_en": "study_work",
      "level": "B",
      "sentence1": "Please **close** the door when you leave.",
      "sentence1_cn": "离开时请关门。",
      "sentence2": "The shop **closes** at six o'clock in the evening.",
      "sentence2_cn": "商店晚上六点关门。"
    },
    {
      "id": 133,
      "word": "collect",
      "phonetic": "/kəˈlekt/",
      "part": "v.",
      "meaning": "收集，采集",
      "topic": "学习&工作动作",
      "topic_en": "study_work",
      "level": "B",
      "sentence1": "He loves to **collect** football cards.",
      "sentence1_cn": "他喜欢收集足球卡。",
      "sentence2": "We **collected** leaves in the park last autumn.",
      "sentence2_cn": "去年秋天我们在公园里收集了树叶。"
    },
    {
      "id": 134,
      "word": "come",
      "phonetic": "/kʌm/",
      "part": "v.",
      "meaning": "来，来到",
      "topic": "学习&工作动作",
      "topic_en": "study_work",
      "level": "B",
      "sentence1": "Please **come** to my birthday party on Saturday.",
      "sentence1_cn": "请来参加我星期六的生日派对。",
      "sentence2": "She **came** home late after her dance class.",
      "sentence2_cn": "舞蹈课后她很晚才回家。"
    },
    {
      "id": 135,
      "word": "cook",
      "phonetic": "/kʊk/",
      "part": "v.",
      "meaning": "烹饪，做饭",
      "topic": "学习&工作动作",
      "topic_en": "study_work",
      "level": "B",
      "sentence1": "My mum **cooks** dinner for us every evening.",
      "sentence1_cn": "我妈妈每天晚上为我们做晚饭。",
      "sentence2": "I **cooked** pasta for the first time last week.",
      "sentence2_cn": "上周我第一次做了意大利面。"
    },
    {
      "id": 136,
      "word": "cut",
      "phonetic": "/kʌt/",
      "part": "v.",
      "meaning": "切，割",
      "topic": "学习&工作动作",
      "topic_en": "study_work",
      "level": "B",
      "sentence1": "Please **cut** the bread into small pieces.",
      "sentence1_cn": "请把面包切成小块。",
      "sentence2": "She **cut** some flowers from the garden for the table.",
      "sentence2_cn": "她从花园里剪了一些花放在桌子上。"
    },
    {
      "id": 137,
      "word": "decide",
      "phonetic": "/dɪˈsaɪd/",
      "part": "v.",
      "meaning": "决定",
      "topic": "学习&工作动作",
      "topic_en": "study_work",
      "level": "B",
      "sentence1": "We **decided** to go to the park after lunch.",
      "sentence1_cn": "我们决定午饭后去公园。",
      "sentence2": "Have you **decided** what to study at university?",
      "sentence2_cn": "你决定好大学要学什么了吗？"
    },
    {
      "id": 138,
      "word": "do",
      "phonetic": "/duː/",
      "part": "v.",
      "meaning": "做，干",
      "topic": "学习&工作动作",
      "topic_en": "study_work",
      "level": "B",
      "sentence1": "I always **do** my homework before dinner.",
      "sentence1_cn": "我总是在晚饭前做作业。",
      "sentence2": "What did you **do** last weekend?",
      "sentence2_cn": "你上周末做了什么？"
    },
    {
      "id": 139,
      "word": "drink",
      "phonetic": "/drɪŋk/",
      "part": "v./n.",
      "meaning": "喝/饮品",
      "topic": "生活&饮食购物",
      "topic_en": "life_shopping",
      "level": "B",
      "sentence1": "You should **drink** eight glasses of water each day.",
      "sentence1_cn": "你每天应该喝八杯水。",
      "sentence2": "What would you like to **drink** with your meal?",
      "sentence2_cn": "用餐时你想喝什么？"
    },
    {
      "id": 140,
      "word": "drive",
      "phonetic": "/draɪv/",
      "part": "v.",
      "meaning": "驾驶，开车",
      "topic": "生活&饮食购物",
      "topic_en": "life_shopping",
      "level": "B",
      "sentence1": "My dad **drives** me to school every morning.",
      "sentence1_cn": "我爸爸每天早上开车送我上学。",
      "sentence2": "She learned to **drive** when she was eighteen.",
      "sentence2_cn": "她十八岁时学会了开车。"
    },
    {
      "id": 141,
      "word": "eat",
      "phonetic": "/iːt/",
      "part": "v.",
      "meaning": "吃",
      "topic": "生活&饮食购物",
      "topic_en": "life_shopping",
      "level": "B",
      "sentence1": "We **eat** breakfast together every morning.",
      "sentence1_cn": "我们每天早上一起吃早饭。",
      "sentence2": "She **ate** a big bowl of noodles for lunch.",
      "sentence2_cn": "她午饭吃了一大碗面条。"
    },
    {
      "id": 142,
      "word": "feed",
      "phonetic": "/fiːd/",
      "part": "v.",
      "meaning": "喂养，喂食",
      "topic": "生活&饮食购物",
      "topic_en": "life_shopping",
      "level": "B",
      "sentence1": "I **feed** my pet cat twice a day.",
      "sentence1_cn": "我每天喂猫咪两次。",
      "sentence2": "She **fed** the ducks at the park last Sunday.",
      "sentence2_cn": "上周日她在公园喂了鸭子。"
    },
    {
      "id": 143,
      "word": "fill",
      "phonetic": "/fɪl/",
      "part": "v.",
      "meaning": "填满，装满",
      "topic": "生活&饮食购物",
      "topic_en": "life_shopping",
      "level": "B",
      "sentence1": "Please **fill** the bottle with cold water.",
      "sentence1_cn": "请把瓶子装满冷水。",
      "sentence2": "She **filled** the bag with books and left for school.",
      "sentence2_cn": "她把书装进包里，然后去上学了。"
    },
    {
      "id": 144,
      "word": "find",
      "phonetic": "/faɪnd/",
      "part": "v.",
      "meaning": "找到，发现",
      "topic": "生活&饮食购物",
      "topic_en": "life_shopping",
      "level": "B",
      "sentence1": "I cannot **find** my school bag anywhere.",
      "sentence1_cn": "我到处找不到我的书包。",
      "sentence2": "She **found** a ten pound note on the street.",
      "sentence2_cn": "她在街上发现了一张十英镑的钞票。"
    },
    {
      "id": 145,
      "word": "fix",
      "phonetic": "/fɪks/",
      "part": "v.",
      "meaning": "修理，安装",
      "topic": "生活&饮食购物",
      "topic_en": "life_shopping",
      "level": "B",
      "sentence1": "Dad **fixed** my bike after it broke.",
      "sentence1_cn": "自行车坏了之后，爸爸帮我修好了。",
      "sentence2": "Can you **fix** the broken chair in the kitchen?",
      "sentence2_cn": "你能修好厨房里那把坏椅子吗？"
    },
    {
      "id": 146,
      "word": "fly",
      "phonetic": "/flaɪ/",
      "part": "v.",
      "meaning": "飞，飞行",
      "topic": "生活&饮食购物",
      "topic_en": "life_shopping",
      "level": "B",
      "sentence1": "Birds **fly** south in autumn.",
      "sentence1_cn": "鸟在秋天往南飞。",
      "sentence2": "We **flew** to Spain for our summer holiday.",
      "sentence2_cn": "我们乘飞机去西班牙度暑假。"
    },
    {
      "id": 147,
      "word": "forgive",
      "phonetic": "/fəˈɡɪv/",
      "part": "v.",
      "meaning": "原谅，宽恕",
      "topic": "生活&饮食购物",
      "topic_en": "life_shopping",
      "level": "B",
      "sentence1": "Please **forgive** me – I did not mean to be late.",
      "sentence1_cn": "请原谅我——我不是故意迟到的。",
      "sentence2": "She **forgave** her friend after their argument.",
      "sentence2_cn": "她原谅了争吵后的朋友。"
    },
    {
      "id": 148,
      "word": "get",
      "phonetic": "/ɡet/",
      "part": "v.",
      "meaning": "得到，获得",
      "topic": "生活&饮食购物",
      "topic_en": "life_shopping",
      "level": "B",
      "sentence1": "I **got** a new book for my birthday.",
      "sentence1_cn": "我生日收到了一本新书。",
      "sentence2": "Can you **get** some milk from the shop?",
      "sentence2_cn": "你能去商店买些牛奶吗？"
    },
    {
      "id": 149,
      "word": "give",
      "phonetic": "/ɡɪv/",
      "part": "v.",
      "meaning": "给，赠送",
      "topic": "生活&饮食购物",
      "topic_en": "life_shopping",
      "level": "B",
      "sentence1": "My grandmother **gave** me a lovely gift.",
      "sentence1_cn": "我祖母给了我一份可爱的礼物。",
      "sentence2": "Please **give** me your homework book.",
      "sentence2_cn": "请把你的作业本给我。"
    },
    {
      "id": 150,
      "word": "go",
      "phonetic": "/ɡəʊ/",
      "part": "v.",
      "meaning": "去，走",
      "topic": "生活&饮食购物",
      "topic_en": "life_shopping",
      "level": "B",
      "sentence1": "We **go** to school by bus every morning.",
      "sentence1_cn": "我们每天早上坐公共汽车上学。",
      "sentence2": "Let's **go** to the park after lunch.",
      "sentence2_cn": "午饭后我们去公园吧。"
    },
    {
      "id": 151,
      "word": "grow",
      "phonetic": "/ɡrəʊ/",
      "part": "v.",
      "meaning": "生长，成长",
      "topic": "生活&饮食购物",
      "topic_en": "life_shopping",
      "level": "B",
      "sentence1": "We **grow** tomatoes in our garden every summer.",
      "sentence1_cn": "我们每年夏天在花园里种番茄。",
      "sentence2": "Children **grow** very quickly in their first few years.",
      "sentence2_cn": "孩子在最初几年里成长非常迅速。"
    },
    {
      "id": 152,
      "word": "hang",
      "phonetic": "/hæŋ/",
      "part": "v.",
      "meaning": "悬挂，吊起",
      "topic": "生活&饮食购物",
      "topic_en": "life_shopping",
      "level": "B",
      "sentence1": "Please **hang** your coat on the hook.",
      "sentence1_cn": "请把你的外套挂在钩子上。",
      "sentence2": "She **hung** a picture of her family on the wall.",
      "sentence2_cn": "她把一张家庭照片挂在墙上。"
    },
    {
      "id": 153,
      "word": "have",
      "phonetic": "/hæv/",
      "part": "v.",
      "meaning": "有，拥有",
      "topic": "生活&饮食购物",
      "topic_en": "life_shopping",
      "level": "B",
      "sentence1": "I **have** two sisters and one brother.",
      "sentence1_cn": "我有两个姐妹和一个兄弟。",
      "sentence2": "Do you **have** a pen I can borrow?",
      "sentence2_cn": "你有钢笔可以借给我吗？"
    },
    {
      "id": 154,
      "word": "hear",
      "phonetic": "/hɪə/",
      "part": "v.",
      "meaning": "听见，听到",
      "topic": "生活&饮食购物",
      "topic_en": "life_shopping",
      "level": "B",
      "sentence1": "Can you **hear** the music from next door?",
      "sentence1_cn": "你能听到隔壁的音乐吗？",
      "sentence2": "She **heard** a strange noise in the garden.",
      "sentence2_cn": "她听到花园里有奇怪的声音。"
    },
    {
      "id": 155,
      "word": "help",
      "phonetic": "/help/",
      "part": "v.",
      "meaning": "帮助",
      "topic": "生活&饮食购物",
      "topic_en": "life_shopping",
      "level": "B",
      "sentence1": "Can you **help** me carry this heavy bag?",
      "sentence1_cn": "你能帮我搬这个重包吗？",
      "sentence2": "She always **helps** her little brother with his reading.",
      "sentence2_cn": "她总是帮助弟弟练习阅读。"
    },
    {
      "id": 156,
      "word": "hide",
      "phonetic": "/haɪd/",
      "part": "v.",
      "meaning": "隐藏，躲藏",
      "topic": "生活&饮食购物",
      "topic_en": "life_shopping",
      "level": "B",
      "sentence1": "The cat **hid** behind the sofa.",
      "sentence1_cn": "猫躲在沙发后面。",
      "sentence2": "I **hid** the birthday present under my bed.",
      "sentence2_cn": "我把生日礼物藏在床底下。"
    },
    {
      "id": 157,
      "word": "hit",
      "phonetic": "/hɪt/",
      "part": "v.",
      "meaning": "打，撞击",
      "topic": "生活&饮食购物",
      "topic_en": "life_shopping",
      "level": "B",
      "sentence1": "She **hit** the ball very hard with her racket.",
      "sentence1_cn": "她用球拍用力打了球。",
      "sentence2": "The ball **hit** the window and broke it.",
      "sentence2_cn": "球打到了窗户，把窗户打碎了。"
    },
    {
      "id": 158,
      "word": "hold",
      "phonetic": "/həʊld/",
      "part": "v.",
      "meaning": "拿着，握住",
      "topic": "生活&饮食购物",
      "topic_en": "life_shopping",
      "level": "B",
      "sentence1": "**Hold** my hand when we cross the road.",
      "sentence1_cn": "过马路时握住我的手。",
      "sentence2": "She **held** the baby carefully in her arms.",
      "sentence2_cn": "她小心地把婴儿抱在怀里。"
    },
    {
      "id": 159,
      "word": "home",
      "phonetic": "/həʊm/",
      "part": "n.",
      "meaning": "家",
      "topic": "出行&环境天气",
      "topic_en": "travel_weather",
      "level": "C",
      "sentence1": "I walked **home** from school with my friend.",
      "sentence1_cn": "我和朋友一起从学校走回家。",
      "sentence2": "There is no place like **home**.",
      "sentence2_cn": "家是最温暖的地方。"
    },
    {
      "id": 160,
      "word": "hospital",
      "phonetic": "/ˈhɒspɪtl/",
      "part": "n.",
      "meaning": "医院",
      "topic": "出行&环境天气",
      "topic_en": "travel_weather",
      "level": "C",
      "sentence1": "She went to the **hospital** to visit her grandmother.",
      "sentence1_cn": "她去医院探望祖母。",
      "sentence2": "The **hospital** is near the town centre.",
      "sentence2_cn": "医院在市中心附近。"
    },
    {
      "id": 161,
      "word": "hotel",
      "phonetic": "/həʊˈtel/",
      "part": "n.",
      "meaning": "酒店，旅馆",
      "topic": "出行&环境天气",
      "topic_en": "travel_weather",
      "level": "C",
      "sentence1": "We stayed in a **hotel** near the beach.",
      "sentence1_cn": "我们住在海边附近的酒店。",
      "sentence2": "The **hotel** has a lovely swimming pool.",
      "sentence2_cn": "这家酒店有一个漂亮的游泳池。"
    },
    {
      "id": 162,
      "word": "house",
      "phonetic": "/haʊs/",
      "part": "n.",
      "meaning": "房子，住宅",
      "topic": "出行&环境天气",
      "topic_en": "travel_weather",
      "level": "C",
      "sentence1": "My **house** has three bedrooms and a garden.",
      "sentence1_cn": "我家有三间卧室和一个花园。",
      "sentence2": "They painted their **house** yellow last summer.",
      "sentence2_cn": "他们去年夏天把房子漆成黄色。"
    },
    {
      "id": 163,
      "word": "lake",
      "phonetic": "/leɪk/",
      "part": "n.",
      "meaning": "湖",
      "topic": "出行&环境天气",
      "topic_en": "travel_weather",
      "level": "C",
      "sentence1": "We went fishing at the **lake** at the weekend.",
      "sentence1_cn": "我们周末去湖边钓鱼。",
      "sentence2": "The **lake** is very beautiful in the morning.",
      "sentence2_cn": "湖在早上非常美丽。"
    },
    {
      "id": 164,
      "word": "land",
      "phonetic": "/lænd/",
      "part": "n.",
      "meaning": "陆地，土地",
      "topic": "出行&环境天气",
      "topic_en": "travel_weather",
      "level": "C",
      "sentence1": "The plane will **land** in twenty minutes.",
      "sentence1_cn": "飞机将在二十分钟后降落。",
      "sentence2": "After two weeks at sea, they saw **land**.",
      "sentence2_cn": "在海上漂了两周后，他们看到了陆地。"
    },
    {
      "id": 165,
      "word": "large",
      "phonetic": "/lɑːdʒ/",
      "part": "adj.",
      "meaning": "大的，巨大的",
      "topic": "出行&环境天气",
      "topic_en": "travel_weather",
      "level": "C",
      "sentence1": "They live in a **large** house with a big garden.",
      "sentence1_cn": "他们住在一栋有大花园的大房子里。",
      "sentence2": "There is a **large** supermarket near our school.",
      "sentence2_cn": "我们学校附近有一家大超市。"
    },
    {
      "id": 166,
      "word": "last",
      "phonetic": "/lɑːst/",
      "part": "adj./v.",
      "meaning": "最后的，上一个的/持续",
      "topic": "出行&环境天气",
      "topic_en": "travel_weather",
      "level": "C",
      "sentence1": "The **last** bus leaves at ten o'clock at night.",
      "sentence1_cn": "最后一班公共汽车晚上十点出发。",
      "sentence2": "The football match **lasted** for ninety minutes.",
      "sentence2_cn": "足球比赛持续了九十分钟。"
    },
    {
      "id": 167,
      "word": "late",
      "phonetic": "/leɪt/",
      "part": "adj.",
      "meaning": "晚的，迟到的",
      "topic": "出行&环境天气",
      "topic_en": "travel_weather",
      "level": "C",
      "sentence1": "The train was **late** because of the storm.",
      "sentence1_cn": "由于暴风雨，火车晚点了。",
      "sentence2": "Please don't be **late** for school tomorrow.",
      "sentence2_cn": "明天上学请不要迟到。"
    },
    {
      "id": 168,
      "word": "left",
      "phonetic": "/left/",
      "part": "adj.",
      "meaning": "左边的",
      "topic": "出行&环境天气",
      "topic_en": "travel_weather",
      "level": "C",
      "sentence1": "Turn **left** at the traffic lights.",
      "sentence1_cn": "在交通灯处左转。",
      "sentence2": "The school is on the **left** side of the road.",
      "sentence2_cn": "学校在路的左边。"
    },
    {
      "id": 169,
      "word": "light",
      "phonetic": "/laɪt/",
      "part": "n./adj.",
      "meaning": "灯，光线/轻的",
      "topic": "出行&环境天气",
      "topic_en": "travel_weather",
      "level": "C",
      "sentence1": "Please turn on the **light** – it is too dark.",
      "sentence1_cn": "请开灯——太黑了。",
      "sentence2": "This bag is very **light** and easy to carry.",
      "sentence2_cn": "这个包很轻，容易携带。"
    },
    {
      "id": 170,
      "word": "like",
      "phonetic": "/laɪk/",
      "part": "v./prep.",
      "meaning": "喜欢/像",
      "topic": "出行&环境天气",
      "topic_en": "travel_weather",
      "level": "C",
      "sentence1": "I **like** reading books about animals.",
      "sentence1_cn": "我喜欢读关于动物的书。",
      "sentence2": "She runs **like** the wind – she is so fast.",
      "sentence2_cn": "她跑得像风一样——她真的很快。"
    },
    {
      "id": 171,
      "word": "live",
      "phonetic": "/lɪv/",
      "part": "v.",
      "meaning": "居住，生活",
      "topic": "出行&环境天气",
      "topic_en": "travel_weather",
      "level": "C",
      "sentence1": "I **live** in a small town near London.",
      "sentence1_cn": "我住在伦敦附近的一个小镇上。",
      "sentence2": "She has **lived** in the same house all her life.",
      "sentence2_cn": "她一生都住在同一栋房子里。"
    },
    {
      "id": 172,
      "word": "long",
      "phonetic": "/lɒŋ/",
      "part": "adj.",
      "meaning": "长的，久的",
      "topic": "出行&环境天气",
      "topic_en": "travel_weather",
      "level": "C",
      "sentence1": "It is a **long** walk from my house to the station.",
      "sentence1_cn": "从我家到车站走路很长。",
      "sentence2": "She has very **long** hair and it is very beautiful.",
      "sentence2_cn": "她有很长的头发，非常漂亮。"
    },
    {
      "id": 173,
      "word": "look",
      "phonetic": "/lʊk/",
      "part": "v.",
      "meaning": "看，看起来",
      "topic": "出行&环境天气",
      "topic_en": "travel_weather",
      "level": "C",
      "sentence1": "**Look** at the birds in the sky!",
      "sentence1_cn": "看天上的鸟！",
      "sentence2": "She **looks** very happy today.",
      "sentence2_cn": "她今天看起来很开心。"
    },
    {
      "id": 174,
      "word": "lose",
      "phonetic": "/luːz/",
      "part": "v.",
      "meaning": "丢失，失去",
      "topic": "出行&环境天气",
      "topic_en": "travel_weather",
      "level": "C",
      "sentence1": "I **lost** my keys somewhere in the house.",
      "sentence1_cn": "我把钥匙丢在房子里某处了。",
      "sentence2": "Our team **lost** the match yesterday by one goal.",
      "sentence2_cn": "我们队昨天以一球之差输了比赛。"
    },
    {
      "id": 175,
      "word": "low",
      "phonetic": "/ləʊ/",
      "part": "adj.",
      "meaning": "低的，矮的",
      "topic": "出行&环境天气",
      "topic_en": "travel_weather",
      "level": "C",
      "sentence1": "The temperature is very **low** in winter.",
      "sentence1_cn": "冬天气温非常低。",
      "sentence2": "Mind your head – that bridge is very **low**.",
      "sentence2_cn": "注意你的头——那座桥非常低。"
    },
    {
      "id": 176,
      "word": "make",
      "phonetic": "/meɪk/",
      "part": "v.",
      "meaning": "制作，使",
      "topic": "出行&环境天气",
      "topic_en": "travel_weather",
      "level": "C",
      "sentence1": "She **makes** her own breakfast every morning.",
      "sentence1_cn": "她每天早上自己做早饭。",
      "sentence2": "Let's **make** a card for our teacher's birthday.",
      "sentence2_cn": "我们来为老师的生日做张贺卡吧。"
    },
    {
      "id": 177,
      "word": "map",
      "phonetic": "/mæp/",
      "part": "n.",
      "meaning": "地图",
      "topic": "出行&环境天气",
      "topic_en": "travel_weather",
      "level": "C",
      "sentence1": "We used a **map** to find our way in the city.",
      "sentence1_cn": "我们用地图在城市里找路。",
      "sentence2": "She drew a **map** of our school for the new student.",
      "sentence2_cn": "她为新同学画了一张学校地图。"
    },
    {
      "id": 178,
      "word": "market",
      "phonetic": "/ˈmɑːkɪt/",
      "part": "n.",
      "meaning": "市场，集市",
      "topic": "出行&环境天气",
      "topic_en": "travel_weather",
      "level": "C",
      "sentence1": "Mum buys fresh vegetables at the **market**.",
      "sentence1_cn": "妈妈在市场买新鲜蔬菜。",
      "sentence2": "The **market** opens every Saturday morning.",
      "sentence2_cn": "市场每周六早上开放。"
    },
    {
      "id": 179,
      "word": "matter",
      "phonetic": "/ˈmætə/",
      "part": "n.",
      "meaning": "事情，问题",
      "topic": "兴趣&健康情绪",
      "topic_en": "hobbies_health",
      "level": "C",
      "sentence1": "What is the **matter**? You look sad.",
      "sentence1_cn": "怎么了？你看起来很难过。",
      "sentence2": "It does not **matter** if you make a small mistake.",
      "sentence2_cn": "犯小错误没关系。"
    },
    {
      "id": 180,
      "word": "may",
      "phonetic": "/meɪ/",
      "part": "modal v.",
      "meaning": "可以，可能",
      "topic": "兴趣&健康情绪",
      "topic_en": "hobbies_health",
      "level": "C",
      "sentence1": "**May** I open the window, please?",
      "sentence1_cn": "我可以打开窗户吗？",
      "sentence2": "It **may** rain this afternoon, so take an umbrella.",
      "sentence2_cn": "今天下午可能下雨，所以带把伞。"
    },
    {
      "id": 181,
      "word": "mean",
      "phonetic": "/miːn/",
      "part": "v.",
      "meaning": "意思是，意味着",
      "topic": "兴趣&健康情绪",
      "topic_en": "hobbies_health",
      "level": "C",
      "sentence1": "What does this word **mean** in English?",
      "sentence1_cn": "这个单词用英语是什么意思？",
      "sentence2": "I did not **mean** to hurt your feelings.",
      "sentence2_cn": "我不是故意伤害你的感情的。"
    },
    {
      "id": 182,
      "word": "meet",
      "phonetic": "/miːt/",
      "part": "v.",
      "meaning": "遇见，见面",
      "topic": "兴趣&健康情绪",
      "topic_en": "hobbies_health",
      "level": "C",
      "sentence1": "I **meet** my friends at the park every Saturday.",
      "sentence1_cn": "我每周六在公园见朋友。",
      "sentence2": "Nice to **meet** you! I'm Tom.",
      "sentence2_cn": "很高兴认识你！我是Tom。"
    },
    {
      "id": 183,
      "word": "milk",
      "phonetic": "/mɪlk/",
      "part": "n.",
      "meaning": "牛奶",
      "topic": "兴趣&健康情绪",
      "topic_en": "hobbies_health",
      "level": "C",
      "sentence1": "I drink a glass of **milk** every morning.",
      "sentence1_cn": "我每天早上喝一杯牛奶。",
      "sentence2": "Please add some **milk** to my tea.",
      "sentence2_cn": "请在我的茶里加一些牛奶。"
    },
    {
      "id": 184,
      "word": "mind",
      "phonetic": "/maɪnd/",
      "part": "v./n.",
      "meaning": "介意/头脑，心思",
      "topic": "兴趣&健康情绪",
      "topic_en": "hobbies_health",
      "level": "C",
      "sentence1": "Do you **mind** if I sit here?",
      "sentence1_cn": "你介意我坐这里吗？",
      "sentence2": "She has a very quick **mind** and learns fast.",
      "sentence2_cn": "她头脑非常敏锐，学东西很快。"
    },
    {
      "id": 185,
      "word": "mix",
      "phonetic": "/mɪks/",
      "part": "v.",
      "meaning": "混合，搅拌",
      "topic": "兴趣&健康情绪",
      "topic_en": "hobbies_health",
      "level": "C",
      "sentence1": "**Mix** the flour and eggs to make a cake.",
      "sentence1_cn": "把面粉和鸡蛋混合在一起做蛋糕。",
      "sentence2": "She **mixed** the colours to make a new shade.",
      "sentence2_cn": "她把颜色混合在一起，调出了新的色调。"
    },
    {
      "id": 186,
      "word": "money",
      "phonetic": "/ˈmʌni/",
      "part": "n.",
      "meaning": "钱，金钱",
      "topic": "兴趣&健康情绪",
      "topic_en": "hobbies_health",
      "level": "C",
      "sentence1": "I save my **money** to buy a new book.",
      "sentence1_cn": "我存钱买一本新书。",
      "sentence2": "She did not have enough **money** to buy the shoes.",
      "sentence2_cn": "她没有足够的钱买那双鞋。"
    },
    {
      "id": 187,
      "word": "month",
      "phonetic": "/mʌnθ/",
      "part": "n.",
      "meaning": "月，月份",
      "topic": "兴趣&健康情绪",
      "topic_en": "hobbies_health",
      "level": "C",
      "sentence1": "My birthday is next **month**.",
      "sentence1_cn": "我的生日在下个月。",
      "sentence2": "We have been studying KET for four **months**.",
      "sentence2_cn": "我们已经学习KET四个月了。"
    },
    {
      "id": 188,
      "word": "morning",
      "phonetic": "/ˈmɔːnɪŋ/",
      "part": "n.",
      "meaning": "早上，上午",
      "topic": "兴趣&健康情绪",
      "topic_en": "hobbies_health",
      "level": "C",
      "sentence1": "I wake up early every **morning**.",
      "sentence1_cn": "我每天早上都早起。",
      "sentence2": "She goes for a run in the **morning** before school.",
      "sentence2_cn": "她上学前在早上跑步。"
    },
    {
      "id": 189,
      "word": "mother",
      "phonetic": "/ˈmʌðə/",
      "part": "n.",
      "meaning": "母亲，妈妈",
      "topic": "兴趣&健康情绪",
      "topic_en": "hobbies_health",
      "level": "C",
      "sentence1": "My **mother** cooks the best food in the world.",
      "sentence1_cn": "我妈妈做的饭是世界上最好吃的。",
      "sentence2": "I gave my **mother** flowers on her birthday.",
      "sentence2_cn": "我在妈妈生日时送了她鲜花。"
    },
    {
      "id": 190,
      "word": "need",
      "phonetic": "/niːd/",
      "part": "v.",
      "meaning": "需要",
      "topic": "兴趣&健康情绪",
      "topic_en": "hobbies_health",
      "level": "C",
      "sentence1": "I **need** to buy a new pencil case.",
      "sentence1_cn": "我需要买一个新的铅笔盒。",
      "sentence2": "Do you **need** help with your homework?",
      "sentence2_cn": "你需要帮助做作业吗？"
    },
    {
      "id": 191,
      "word": "new",
      "phonetic": "/njuː/",
      "part": "adj.",
      "meaning": "新的",
      "topic": "兴趣&健康情绪",
      "topic_en": "hobbies_health",
      "level": "C",
      "sentence1": "She got a **new** bicycle for her birthday.",
      "sentence1_cn": "她生日收到了一辆新自行车。",
      "sentence2": "There is a **new** student in our class today.",
      "sentence2_cn": "今天我们班来了一位新同学。"
    },
    {
      "id": 192,
      "word": "night",
      "phonetic": "/naɪt/",
      "part": "n.",
      "meaning": "夜晚，晚上",
      "topic": "兴趣&健康情绪",
      "topic_en": "hobbies_health",
      "level": "C",
      "sentence1": "She reads a book every **night** before bed.",
      "sentence1_cn": "她每晚睡前读一本书。",
      "sentence2": "The stars are beautiful on a clear **night**.",
      "sentence2_cn": "晴朗的夜晚星星非常美丽。"
    },
    {
      "id": 193,
      "word": "no",
      "phonetic": "/nəʊ/",
      "part": "adv.",
      "meaning": "不，不是",
      "topic": "兴趣&健康情绪",
      "topic_en": "hobbies_health",
      "level": "C",
      "sentence1": "**No**, I do not want any more cake, thank you.",
      "sentence1_cn": "不，我不想再要蛋糕了，谢谢。",
      "sentence2": "She said **no** to the extra homework.",
      "sentence2_cn": "她对额外的作业说了不。"
    },
    {
      "id": 194,
      "word": "noise",
      "phonetic": "/nɔɪz/",
      "part": "n.",
      "meaning": "噪音，喧闹声",
      "topic": "兴趣&健康情绪",
      "topic_en": "hobbies_health",
      "level": "C",
      "sentence1": "Please do not make a **noise** in the library.",
      "sentence1_cn": "在图书馆请不要制造噪音。",
      "sentence2": "I heard a loud **noise** outside my window.",
      "sentence2_cn": "我听到窗外有很大的噪音。"
    },
    {
      "id": 195,
      "word": "none",
      "phonetic": "/nʌn/",
      "part": "pron.",
      "meaning": "没有一个，毫无",
      "topic": "兴趣&健康情绪",
      "topic_en": "hobbies_health",
      "level": "C",
      "sentence1": "**None** of the students knew the answer.",
      "sentence1_cn": "没有一个学生知道答案。",
      "sentence2": "There is **none** of the cake left.",
      "sentence2_cn": "蛋糕一点都没有剩下了。"
    },
    {
      "id": 196,
      "word": "nor",
      "phonetic": "/nɔː/",
      "part": "conj.",
      "meaning": "也不",
      "topic": "兴趣&健康情绪",
      "topic_en": "hobbies_health",
      "level": "C",
      "sentence1": "She cannot swim, **nor** can she ride a bike.",
      "sentence1_cn": "她不会游泳，也不会骑自行车。",
      "sentence2": "I do not like coffee, **nor** does my sister.",
      "sentence2_cn": "我不喜欢咖啡，我姐姐也不喜欢。"
    },
    {
      "id": 197,
      "word": "not",
      "phonetic": "/nɒt/",
      "part": "adv.",
      "meaning": "不，没有",
      "topic": "兴趣&健康情绪",
      "topic_en": "hobbies_health",
      "level": "C",
      "sentence1": "She is **not** ready for the test yet.",
      "sentence1_cn": "她还没有为考试做好准备。",
      "sentence2": "I did **not** finish my homework last night.",
      "sentence2_cn": "我昨晚没有完成作业。"
    },
    {
      "id": 198,
      "word": "now",
      "phonetic": "/naʊ/",
      "part": "adv.",
      "meaning": "现在，此刻",
      "topic": "兴趣&健康情绪",
      "topic_en": "hobbies_health",
      "level": "C",
      "sentence1": "We are studying English **now**.",
      "sentence1_cn": "我们现在正在学习英语。",
      "sentence2": "**Now** is a good time to start your revision.",
      "sentence2_cn": "现在是开始复习的好时机。"
    }
  ]
}